[ {
  "id" : "5105378d-37b3-4b31-96c6-950b1c6122e5",
  "site" : "github",
  "username" : "nani",
  "ciphertext" : "ihzwArsVHUP1whTw1mlctDBXoRoAHFbSxk4n",
  "salt" : "DTkG0VeQXVxuheEbGAVEwA==",
  "iv" : "tvHxK16ghEwETpo9",
  "createdAt" : 1765265745650
}, {
  "id" : "b04b5ec6-94a0-40ac-a0ca-8a493f02fab7",
  "site" : "Insta",
  "username" : "mine",
  "ciphertext" : "wK6RU05emXBc/qvLeGNKwCon4iqAJ9kTLqtE",
  "salt" : "z2NXebh0WVD7478FkzMiaA==",
  "iv" : "glfIoHoDCRtz8738",
  "createdAt" : 1765265832541
}, {
  "id" : "72e92fb0-5f07-4653-9842-3af3af19d70f",
  "site" : "Insta",
  "username" : "mine",
  "ciphertext" : "w+/zXKItC7445SZJD5Iy2yduV93FHBYif9kN",
  "salt" : "1ln9t8xF+J8ZIJu/mNV6Uw==",
  "iv" : "lMxCA6X9ujjGtIzA",
  "createdAt" : 1765265841052
}, {
  "id" : "04ac63ed-ec65-4fad-90d0-eb0bb2d54bbb",
  "site" : "twitter",
  "username" : "",
  "ciphertext" : "hq5KlODEJK8eNJEN1l+aYdD15pqsJDu7K8Yb",
  "salt" : "e39egqA0akL0FFMIZ8a0bQ==",
  "iv" : "7let7p9puezLfgOo",
  "createdAt" : 1765266166151
}, {
  "id" : "0523448f-b4e6-467b-bedf-e9b4a420ef31",
  "site" : "insta",
  "username" : "",
  "ciphertext" : "4ZmTzHgk9T8h642+3NDXyxtbfOEikq/LFw==",
  "salt" : "IqXjs76typMatvTLDIeAIw==",
  "iv" : "ishkUqwE1XSDYd8q",
  "createdAt" : 1765269903501
} ]